gsheets/__init__.py
gsheets/api.py
gsheets/backend.py
gsheets/coordinates.py
gsheets/export.py
gsheets/models.py
gsheets/oauth2.py
gsheets/tools.py
gsheets/urls.py
gsheets-0.6.1.dist-info/LICENSE.txt
gsheets-0.6.1.dist-info/METADATA
gsheets-0.6.1.dist-info/WHEEL
gsheets-0.6.1.dist-info/top_level.txt
gsheets-0.6.1.dist-info/RECORD
