Metadata-Version: 2.1
Name: gsheets
Version: 0.6.1
Summary: Pythonic wrapper for the Google Sheets API
Home-page: https://github.com/xflr6/gsheets
Author: Sebastian Bank
Author-email: sebastian.bank@uni-leipzig.de
License: MIT
Project-URL: Documentation, https://gsheets.readthedocs.io
Project-URL: Changelog, https://gsheets.readthedocs.io/en/latest/changelog.html
Project-URL: Issue Tracker, https://github.com/xflr6/gsheets/issues
Project-URL: CI, https://github.com/xflr6/gsheets/actions
Project-URL: Coverage, https://codecov.io/gh/xflr6/gsheets
Keywords: spreadhseets google api v4 wrapper csv pandas
Platform: any
Classifier: Development Status :: 4 - Beta
Classifier: Intended Audience :: Developers
Classifier: Intended Audience :: Science/Research
Classifier: License :: OSI Approved :: MIT License
Classifier: Operating System :: OS Independent
Classifier: Programming Language :: Python :: 3
Classifier: Programming Language :: Python :: 3.7
Classifier: Programming Language :: Python :: 3.8
Classifier: Programming Language :: Python :: 3.9
Classifier: Programming Language :: Python :: 3.10
Classifier: Topic :: Internet :: WWW/HTTP
Classifier: Topic :: Office/Business :: Financial :: Spreadsheet
Requires-Python: >=3.7
Provides-Extra: dev
Provides-Extra: test
Provides-Extra: docs
License-File: LICENSE.txt
